alacritty_styles/__init__.py
alacritty_styles/colorscheme.py
alacritty_styles/main.py
alacritty_styles-0.1.1.dist-info/entry_points.txt
alacritty_styles-0.1.1.dist-info/WHEEL
alacritty_styles-0.1.1.dist-info/METADATA
alacritty_styles-0.1.1.dist-info/RECORD
