Metadata-Version: 2.1
Name: alacritty-styles
Version: 0.1.1
Summary: A simple program for changing Alacritty colors.
License: MIT
Author: Bruno Silva Oliveira
Author-email: brunooliveira095@protonmail.com
Requires-Python: >=3.10,<4.0
Classifier: License :: OSI Approved :: MIT License
Classifier: Programming Language :: Python :: 3
Requires-Dist: click (>=8.1.2,<9.0.0)
Requires-Dist: requests (>=2.27.1,<3.0.0)
Requires-Dist: ruamel.yaml (>=0.17.21,<0.18.0)
